pyodb/__init__.py
pyodb/_util.py
pyodb/error.py
pyodb/pyodb.py
pyodb/schema/__init__.py
pyodb/schema/_base_schema.py
pyodb/schema/shard_schema.py
pyodb/schema/unified_schema.py
pyodb/schema/base/__init__.py
pyodb/schema/base/_operators.py
pyodb/schema/base/_sql_builders.py
pyodb/schema/base/_table.py
pyodb/schema/base/_type_defs.py
pyodb-0.1.4.dist-info/METADATA
pyodb-0.1.4.dist-info/WHEEL
pyodb-0.1.4.dist-info/licenses/LICENSE
pyodb-0.1.4.dist-info/RECORD
