Metadata-Version: 2.1
Name: pyodb
Version: 0.1.4
Summary: Python Object DataBase (PyODB) is an ORM library aiming to be as simple to use as possible.
Project-URL: Homepage, https://github.com/NeoSecundus/PyODB
Project-URL: Bug Tracker, https://github.com/NeoSecundus/PyODB/issues
Project-URL: Changelog, https://github.com/NeoSecundus/PyODB/blob/main/CHANGELOG.md
Author-email: Nikolas Teuschl <nikolas.teuschl@alpha-origin.biz>
License: MIT License
License-File: LICENSE
Keywords: cache,caching,database,datacache,orm,sqlite,sqlite3
Classifier: License :: OSI Approved :: MIT License
Classifier: Operating System :: OS Independent
Classifier: Programming Language :: Python :: 3
Requires-Python: >=3.10
